{
  "type": "api",
  "version": "v4.5.0",
  "data": {
    "id": "75249d56-b10c-422d-89ce-102d8e1643c9",
    "name": "AttendanceAPI",
    "context": "/attendance",
    "version": "1.0.0",
    "provider": "admin",
    "lifeCycleStatus": "PUBLISHED",
    "responseCachingEnabled": false,
    "cacheTimeout": 300,
    "hasThumbnail": false,
    "isDefaultVersion": false,
    "isRevision": false,
    "revisionId": 0,
    "enableSchemaValidation": false,
    "enableSubscriberVerification": false,
    "type": "HTTP",
    "audiences": [
      "all"
    ],
    "transport": [
      "http",
      "https"
    ],
    "tags": [],
    "policies": [
      "Unlimited"
    ],
    "organizationPolicies": [],
    "authorizationHeader": "Authorization",
    "apiKeyHeader": "ApiKey",
    "securityScheme": [
      "oauth_basic_auth_api_key_mandatory",
      "oauth2"
    ],
    "visibility": "PUBLIC",
    "visibleRoles": [],
    "visibleTenants": [],
    "visibleOrganizations": [
      "none"
    ],
    "mediationPolicies": [],
    "subscriptionAvailability": "CURRENT_TENANT",
    "subscriptionAvailableTenants": [],
    "additionalProperties": [
      {
        "name": "subdominio",
        "value": "rrhh-empleados",
        "display": true
      }
    ],
    "additionalPropertiesMap": {
      "subdominio__display": {
        "name": "subdominio",
        "value": "rrhh-empleados",
        "display": false
      }
    },
    "accessControl": "NONE",
    "accessControlRoles": [],
    "businessInformation": {},
    "corsConfiguration": {
      "corsConfigurationEnabled": false,
      "accessControlAllowOrigins": [
        "*"
      ],
      "accessControlAllowCredentials": false,
      "accessControlAllowHeaders": [
        "authorization",
        "Access-Control-Allow-Origin",
        "Content-Type",
        "SOAPAction",
        "apikey",
        "Internal-Key"
      ],
      "accessControlAllowMethods": [
        "GET",
        "PUT",
        "POST",
        "DELETE",
        "PATCH",
        "OPTIONS"
      ]
    },
    "websubSubscriptionConfiguration": {
      "enable": false,
      "secret": "",
      "signingAlgorithm": "SHA1",
      "signatureHeader": "x-hub-signature"
    },
    "createdTime": "1765044737612",
    "lastUpdatedTimestamp": "1765044737807",
    "lastUpdatedTime": "2025-12-06 19:12:17.807",
    "endpointConfig": {
      "endpoint_type": "http",
      "sandbox_endpoints": {
        "url": "https://run.mocky.io/v3/e315b78bbc026fa5796ba36fedb23383"
      },
      "production_endpoints": {
        "url": "https://run.mocky.io/v3/721aff1d03557a94b9a3d02b388e4c4d"
      }
    },
    "endpointImplementationType": "ENDPOINT",
    "subtypeConfiguration": {
      "subtype": "DEFAULT"
    },
    "scopes": [],
    "operations": [
      {
        "id": "",
        "target": "/*",
        "verb": "GET",
        "authType": "Application \u0026 Application User",
        "throttlingPolicy": "Unlimited",
        "scopes": [],
        "usedProductIds": [],
        "operationPolicies": {
          "request": [],
          "response": [],
          "fault": []
        }
      },
      {
        "id": "",
        "target": "/*",
        "verb": "POST",
        "authType": "Application \u0026 Application User",
        "throttlingPolicy": "Unlimited",
        "scopes": [],
        "usedProductIds": [],
        "operationPolicies": {
          "request": [],
          "response": [],
          "fault": []
        }
      }
    ],
    "categories": [],
    "keyManagers": [
      "all"
    ],
    "advertiseInfo": {
      "advertised": false,
      "apiOwner": "admin",
      "vendor": "WSO2"
    },
    "gatewayVendor": "wso2",
    "gatewayType": "wso2/synapse",
    "asyncTransportProtocols": [],
    "egress": false,
    "organizationId": "carbon.super"
  }
}